<annotation>
  <folder>RSDD-SAR</folder>
  <filename>116_47_42.xml</filename>
  <polarization>VV</polarization>
  <resolution>10</resolution>
  <size>
    <width>512</width>
    <height>512</height>
    <depth>3</depth>
  </size>
  <segmented>0</segmented>
  <object>
    <type>robndbox</type>
    <name>ship</name>
    <difficult>0</difficult>
    <robndbox>
      <cx>247.481</cx>
      <cy>318.2104</cy>
      <h>19.86496925354004</h>
      <w>6.687012195587158</w>
      <angle>1.5704643637650182</angle>
    </robndbox>
  </object>
  <object>
    <type>robndbox</type>
    <name>ship</name>
    <difficult>0</difficult>
    <robndbox>
      <cx>42.0949</cx>
      <cy>350.5047</cy>
      <h>15.049692153930664</h>
      <w>5.655002593994141</w>
      <angle>1.5604672565070243</angle>
    </robndbox>
  </object>
  <object>
    <type>robndbox</type>
    <name>ship</name>
    <difficult>0</difficult>
    <robndbox>
      <cx>419.0994</cx>
      <cy>291.6763</cy>
      <h>16.649412155151367</h>
      <w>6.2399468421936035</w>
      <angle>1.5704636979747457</angle>
    </robndbox>
  </object>
</annotation>
