<annotation>
  <folder>RSDD-SAR</folder>
  <filename>121_12_10.xml</filename>
  <polarization>HH</polarization>
  <resolution>5</resolution>
  <size>
    <width>512</width>
    <height>512</height>
    <depth>3</depth>
  </size>
  <segmented>0</segmented>
  <object>
    <type>robndbox</type>
    <name>ship</name>
    <difficult>0</difficult>
    <robndbox>
      <cx>340.0401</cx>
      <cy>432.6322</cy>
      <h>50.84296798706055</h>
      <w>13.120491027832031</w>
      <angle>-0.6085989546893851</angle>
    </robndbox>
  </object>
</annotation>
