<annotation>
  <folder>RSDD-SAR</folder>
  <filename>12_12_9.xml</filename>
  <polarization>HH</polarization>
  <resolution>25</resolution>
  <size>
    <width>512</width>
    <height>512</height>
    <depth>3</depth>
  </size>
  <segmented>0</segmented>
  <object>
    <type>robndbox</type>
    <name>ship</name>
    <difficult>0</difficult>
    <robndbox>
      <cx>76.5</cx>
      <cy>353.5</cy>
      <h>42.249534606933594</h>
      <w>12.040743827819824</w>
      <angle>-1.4994890151526696</angle>
    </robndbox>
  </object>
</annotation>
