<annotation>
  <folder>RSDD-SAR</folder>
  <filename>12_39_24.xml</filename>
  <polarization>HH</polarization>
  <resolution>25</resolution>
  <size>
    <width>512</width>
    <height>512</height>
    <depth>3</depth>
  </size>
  <segmented>0</segmented>
  <object>
    <type>robndbox</type>
    <name>ship</name>
    <difficult>0</difficult>
    <robndbox>
      <cx>188.9347</cx>
      <cy>341.9057</cy>
      <h>45.1724739074707</h>
      <w>16.403514862060547</w>
      <angle>-1.1102304130095701</angle>
    </robndbox>
  </object>
</annotation>
