<annotation>
  <folder>RSDD-SAR</folder>
  <filename>138_30_2.xml</filename>
  <polarization>HV</polarization>
  <resolution>10</resolution>
  <size>
    <width>512</width>
    <height>512</height>
    <depth>3</depth>
  </size>
  <segmented>0</segmented>
  <object>
    <type>robndbox</type>
    <name>ship</name>
    <difficult>0</difficult>
    <robndbox>
      <cx>188.407</cx>
      <cy>428.2992</cy>
      <h>27.628084182739258</h>
      <w>7.7450690269470215</w>
      <angle>-0.3782989702105022</angle>
    </robndbox>
  </object>
  <object>
    <type>robndbox</type>
    <name>ship</name>
    <difficult>0</difficult>
    <robndbox>
      <cx>23.0249</cx>
      <cy>221.5481</cy>
      <h>31.61459732055664</h>
      <w>8.522605895996094</w>
      <angle>-0.2882995717001464</angle>
    </robndbox>
  </object>
  <object>
    <type>robndbox</type>
    <name>ship</name>
    <difficult>0</difficult>
    <robndbox>
      <cx>202.9154</cx>
      <cy>127.545</cy>
      <h>28.701391220092773</h>
      <w>7.242406368255615</w>
      <angle>-0.36829893347530906</angle>
    </robndbox>
  </object>
  <object>
    <type>robndbox</type>
    <name>ship</name>
    <difficult>0</difficult>
    <robndbox>
      <cx>418.7542</cx>
      <cy>148.8774</cy>
      <h>30.882511138916016</h>
      <w>7.956297397613525</w>
      <angle>-0.3282989196925916</angle>
    </robndbox>
  </object>
  <object>
    <type>robndbox</type>
    <name>ship</name>
    <difficult>0</difficult>
    <robndbox>
      <cx>329.0</cx>
      <cy>278.5</cy>
      <h>30.64377784729004</h>
      <w>8.82936954498291</w>
      <angle>-0.468299167669185</angle>
    </robndbox>
  </object>
</annotation>
