<annotation>
  <folder>RSDD-SAR</folder>
  <filename>139_26_65.xml</filename>
  <polarization>HH</polarization>
  <resolution>10</resolution>
  <size>
    <width>512</width>
    <height>512</height>
    <depth>3</depth>
  </size>
  <segmented>0</segmented>
  <object>
    <type>robndbox</type>
    <name>ship</name>
    <difficult>0</difficult>
    <robndbox>
      <cx>103.0243</cx>
      <cy>25.7984</cy>
      <h>38.28300476074219</h>
      <w>15.114896774291992</w>
      <angle>0.8910338461950136</angle>
    </robndbox>
  </object>
</annotation>
