<annotation>
  <folder>RSDD-SAR</folder>
  <filename>192_27_22.xml</filename>
  <polarization>DH</polarization>
  <resolution>3</resolution>
  <size>
    <width>512</width>
    <height>512</height>
    <depth>3</depth>
  </size>
  <segmented>0</segmented>
  <object>
    <type>robndbox</type>
    <name>ship</name>
    <difficult>0</difficult>
    <robndbox>
      <cx>152.7392</cx>
      <cy>412.9769</cy>
      <h>47.40791320800781</h>
      <w>13.859975814819336</w>
      <angle>0.958368944880468</angle>
    </robndbox>
  </object>
</annotation>
