<annotation>
  <folder>RSDD-SAR</folder>
  <filename>21_16_22.xml</filename>
  <polarization>VV</polarization>
  <resolution>5</resolution>
  <size>
    <width>512</width>
    <height>512</height>
    <depth>3</depth>
  </size>
  <segmented>0</segmented>
  <object>
    <type>robndbox</type>
    <name>ship</name>
    <difficult>0</difficult>
    <robndbox>
      <cx>326.6596</cx>
      <cy>41.0</cy>
      <h>26.555578231811523</h>
      <w>12.9151029586792</w>
      <angle>-0.6241948255070526</angle>
    </robndbox>
  </object>
</annotation>
