<annotation>
  <folder>RSDD-SAR</folder>
  <filename>24_40_13.xml</filename>
  <polarization>VH</polarization>
  <resolution>25</resolution>
  <size>
    <width>512</width>
    <height>512</height>
    <depth>3</depth>
  </size>
  <segmented>0</segmented>
  <object>
    <type>robndbox</type>
    <name>ship</name>
    <difficult>0</difficult>
    <robndbox>
      <cx>402.5687</cx>
      <cy>128.1441</cy>
      <h>37.92308807373047</h>
      <w>11.237398147583008</w>
      <angle>-0.8999920543117675</angle>
    </robndbox>
  </object>
</annotation>
