<annotation>
  <folder>RSDD-SAR</folder>
  <filename>26_8_4.xml</filename>
  <polarization>VH</polarization>
  <resolution>25</resolution>
  <size>
    <width>512</width>
    <height>512</height>
    <depth>3</depth>
  </size>
  <segmented>0</segmented>
  <object>
    <type>robndbox</type>
    <name>ship</name>
    <difficult>0</difficult>
    <robndbox>
      <cx>419.2027</cx>
      <cy>471.8919</cy>
      <h>50.71470260620117</h>
      <w>13.934649467468262</w>
      <angle>0.2536728349565567</angle>
    </robndbox>
  </object>
</annotation>
