<annotation>
  <folder>RSDD-SAR</folder>
  <filename>29_40_15.xml</filename>
  <polarization>HV</polarization>
  <resolution>25</resolution>
  <size>
    <width>512</width>
    <height>512</height>
    <depth>3</depth>
  </size>
  <segmented>0</segmented>
  <object>
    <type>robndbox</type>
    <name>ship</name>
    <difficult>0</difficult>
    <robndbox>
      <cx>190.5</cx>
      <cy>467.5</cy>
      <h>18.025482177734375</h>
      <w>6.714151859283447</w>
      <angle>-1.3708398005651312</angle>
    </robndbox>
  </object>
  <object>
    <type>robndbox</type>
    <name>ship</name>
    <difficult>0</difficult>
    <robndbox>
      <cx>320.6513</cx>
      <cy>217.3319</cy>
      <h>10.571587562561035</h>
      <w>4.151900768280029</w>
      <angle>-1.2580038955758868</angle>
    </robndbox>
  </object>
  <object>
    <type>robndbox</type>
    <name>ship</name>
    <difficult>0</difficult>
    <robndbox>
      <cx>491.5031</cx>
      <cy>272.6276</cy>
      <h>10.444485664367676</h>
      <w>4.313591957092285</w>
      <angle>0.9899556998844891</angle>
    </robndbox>
  </object>
  <object>
    <type>robndbox</type>
    <name>ship</name>
    <difficult>0</difficult>
    <robndbox>
      <cx>468.8735</cx>
      <cy>336.029</cy>
      <h>8.339980125427246</h>
      <w>5.04490852355957</w>
      <angle>0.5499558478802177</angle>
    </robndbox>
  </object>
  <object>
    <type>robndbox</type>
    <name>ship</name>
    <difficult>0</difficult>
    <robndbox>
      <cx>490.5652</cx>
      <cy>374.4565</cy>
      <h>7.941681385040283</h>
      <w>4.907468318939209</w>
      <angle>-1.4383023231863674</angle>
    </robndbox>
  </object>
  <object>
    <type>robndbox</type>
    <name>ship</name>
    <difficult>0</difficult>
    <robndbox>
      <cx>347.459</cx>
      <cy>417.9087</cy>
      <h>6.196061611175537</h>
      <w>3.881495237350464</w>
      <angle>-0.8108386089216755</angle>
    </robndbox>
  </object>
  <object>
    <type>robndbox</type>
    <name>ship</name>
    <difficult>0</difficult>
    <robndbox>
      <cx>434.9753</cx>
      <cy>348.9753</cy>
      <h>6.67152214050293</h>
      <w>4.503966331481934</w>
      <angle>0.599954866423206</angle>
    </robndbox>
  </object>
  <object>
    <type>robndbox</type>
    <name>ship</name>
    <difficult>0</difficult>
    <robndbox>
      <cx>354.7124</cx>
      <cy>459.5202</cy>
      <h>12.044966697692871</h>
      <w>4.721916198730469</w>
      <angle>-0.6508375551053962</angle>
    </robndbox>
  </object>
  <object>
    <type>robndbox</type>
    <name>ship</name>
    <difficult>0</difficult>
    <robndbox>
      <cx>380.0</cx>
      <cy>301.5</cy>
      <h>8.605384826660156</h>
      <w>3.866098403930664</w>
      <angle>-0.9808365036798398</angle>
    </robndbox>
  </object>
  <object>
    <type>robndbox</type>
    <name>ship</name>
    <difficult>0</difficult>
    <robndbox>
      <cx>167.009</cx>
      <cy>291.6431</cy>
      <h>8.653810501098633</h>
      <w>6.068385601043701</w>
      <angle>-1.5608388507028743</angle>
    </robndbox>
  </object>
</annotation>
