<annotation>
  <folder>RSDD-SAR</folder>
  <filename>44_14_23.xml</filename>
  <polarization>VH</polarization>
  <resolution>5</resolution>
  <size>
    <width>512</width>
    <height>512</height>
    <depth>3</depth>
  </size>
  <segmented>0</segmented>
  <object>
    <type>robndbox</type>
    <name>ship</name>
    <difficult>0</difficult>
    <robndbox>
      <cx>234.9608</cx>
      <cy>453.4608</cy>
      <h>49.17759323120117</h>
      <w>9.121149063110352</w>
      <angle>-0.28497887613692674</angle>
    </robndbox>
  </object>
</annotation>
