<annotation>
  <folder>RSDD-SAR</folder>
  <filename>55_22_34.xml</filename>
  <polarization>VV</polarization>
  <resolution>25</resolution>
  <size>
    <width>512</width>
    <height>512</height>
    <depth>3</depth>
  </size>
  <segmented>0</segmented>
  <object>
    <type>robndbox</type>
    <name>ship</name>
    <difficult>0</difficult>
    <robndbox>
      <cx>253.6232</cx>
      <cy>391.1785</cy>
      <h>43.98040008544922</h>
      <w>11.499398231506348</w>
      <angle>-1.4821427983533044</angle>
    </robndbox>
  </object>
  <object>
    <type>robndbox</type>
    <name>ship</name>
    <difficult>0</difficult>
    <robndbox>
      <cx>389.0025</cx>
      <cy>94.4566</cy>
      <h>49.07669448852539</h>
      <w>14.144859313964844</w>
      <angle>-1.4489546845858186</angle>
    </robndbox>
  </object>
  <object>
    <type>robndbox</type>
    <name>ship</name>
    <difficult>0</difficult>
    <robndbox>
      <cx>498.6619</cx>
      <cy>297.9881</cy>
      <h>44.330501556396484</h>
      <w>10.743524551391602</w>
      <angle>-1.3854481379610837</angle>
    </robndbox>
  </object>
</annotation>
