<annotation>
  <folder>RSDD-SAR</folder>
  <filename>64_2_4.xml</filename>
  <polarization>HH</polarization>
  <resolution>3</resolution>
  <size>
    <width>512</width>
    <height>512</height>
    <depth>3</depth>
  </size>
  <segmented>0</segmented>
  <object>
    <type>robndbox</type>
    <name>ship</name>
    <difficult>0</difficult>
    <robndbox>
      <cx>345.5835</cx>
      <cy>444.6165</cy>
      <h>105.62080383300781</h>
      <w>20.801681518554688</w>
      <angle>-0.47364546355751913</angle>
    </robndbox>
  </object>
</annotation>
