<annotation>
  <folder>RSDD-SAR</folder>
  <filename>72_2_6.xml</filename>
  <polarization>HH</polarization>
  <resolution>3</resolution>
  <size>
    <width>512</width>
    <height>512</height>
    <depth>3</depth>
  </size>
  <segmented>0</segmented>
  <object>
    <type>robndbox</type>
    <name>ship</name>
    <difficult>0</difficult>
    <robndbox>
      <cx>161.2432</cx>
      <cy>187.2838</cy>
      <h>87.0</h>
      <w>28.0</w>
      <angle>-1.5707963267948966</angle>
    </robndbox>
  </object>
  <object>
    <type>robndbox</type>
    <name>ship</name>
    <difficult>0</difficult>
    <robndbox>
      <cx>296.3568</cx>
      <cy>19.0658</cy>
      <h>37.28400802612305</h>
      <w>10.691201210021973</w>
      <angle>-0.10920331997286259</angle>
    </robndbox>
  </object>
  <object>
    <type>robndbox</type>
    <name>ship</name>
    <difficult>0</difficult>
    <robndbox>
      <cx>290.8116</cx>
      <cy>32.1917</cy>
      <h>55.006996154785156</h>
      <w>9.644994735717773</w>
      <angle>-0.13920329702038736</angle>
    </robndbox>
  </object>
  <object>
    <type>robndbox</type>
    <name>ship</name>
    <difficult>0</difficult>
    <robndbox>
      <cx>98.3069</cx>
      <cy>165.6481</cy>
      <h>81.73229217529297</h>
      <w>27.767301559448242</w>
      <angle>1.550796652798674</angle>
    </robndbox>
  </object>
</annotation>
