<annotation>
  <folder>RSDD-SAR</folder>
  <filename>75_23_14.xml</filename>
  <polarization>HH</polarization>
  <resolution>3</resolution>
  <size>
    <width>512</width>
    <height>512</height>
    <depth>3</depth>
  </size>
  <segmented>0</segmented>
  <object>
    <type>robndbox</type>
    <name>ship</name>
    <difficult>0</difficult>
    <robndbox>
      <cx>463.1196</cx>
      <cy>288.2721</cy>
      <h>38.05314636230469</h>
      <w>12.387495040893555</w>
      <angle>0.7028145366794999</angle>
    </robndbox>
  </object>
</annotation>
