<annotation>
  <folder>RSDD-SAR</folder>
  <filename>80_25_28.xml</filename>
  <polarization>VV</polarization>
  <resolution>3</resolution>
  <size>
    <width>512</width>
    <height>512</height>
    <depth>3</depth>
  </size>
  <segmented>0</segmented>
  <object>
    <type>robndbox</type>
    <name>ship</name>
    <difficult>0</difficult>
    <robndbox>
      <cx>184.6019</cx>
      <cy>254.3576</cy>
      <h>13.0972900390625</h>
      <w>8.31699275970459</w>
      <angle>0.513646342867591</angle>
    </robndbox>
  </object>
  <object>
    <type>robndbox</type>
    <name>ship</name>
    <difficult>0</difficult>
    <robndbox>
      <cx>323.4623</cx>
      <cy>11.9623</cy>
      <h>15.059712409973145</h>
      <w>5.848422050476074</w>
      <angle>0.8509319665006003</angle>
    </robndbox>
  </object>
</annotation>
