<annotation>
  <folder>RSDD-SAR</folder>
  <filename>83_15_12.xml</filename>
  <polarization>VV</polarization>
  <resolution>3</resolution>
  <size>
    <width>512</width>
    <height>512</height>
    <depth>3</depth>
  </size>
  <segmented>0</segmented>
  <object>
    <type>robndbox</type>
    <name>ship</name>
    <difficult>0</difficult>
    <robndbox>
      <cx>322.0234</cx>
      <cy>150.7147</cy>
      <h>25.051237106323242</h>
      <w>11.671820640563965</w>
      <angle>1.0121689933787854</angle>
    </robndbox>
  </object>
  <object>
    <type>robndbox</type>
    <name>ship</name>
    <difficult>0</difficult>
    <robndbox>
      <cx>213.0097</cx>
      <cy>18.1763</cy>
      <h>27.966190338134766</h>
      <w>11.696702003479004</w>
      <angle>1.017518285323346</angle>
    </robndbox>
  </object>
  <object>
    <type>robndbox</type>
    <name>ship</name>
    <difficult>0</difficult>
    <robndbox>
      <cx>478.2382</cx>
      <cy>322.305</cy>
      <h>29.16720962524414</h>
      <w>13.855396270751953</w>
      <angle>1.1575162030339856</angle>
    </robndbox>
  </object>
</annotation>
