<annotation>
  <folder>RSDD-SAR</folder>
  <filename>87_4_1.xml</filename>
  <polarization>VV</polarization>
  <resolution>3</resolution>
  <size>
    <width>512</width>
    <height>512</height>
    <depth>3</depth>
  </size>
  <segmented>0</segmented>
  <object>
    <type>robndbox</type>
    <name>ship</name>
    <difficult>0</difficult>
    <robndbox>
      <cx>18.7297</cx>
      <cy>136.5215</cy>
      <h>37.154502868652344</h>
      <w>11.55530834197998</w>
      <angle>0.5754248890966497</angle>
    </robndbox>
  </object>
  <object>
    <type>robndbox</type>
    <name>ship</name>
    <difficult>0</difficult>
    <robndbox>
      <cx>250.4595</cx>
      <cy>335.7838</cy>
      <h>115.43217468261719</h>
      <w>19.37548065185547</w>
      <angle>0.5150727985264646</angle>
    </robndbox>
  </object>
  <object>
    <type>robndbox</type>
    <name>ship</name>
    <difficult>0</difficult>
    <robndbox>
      <cx>126.8608</cx>
      <cy>275.0593</cy>
      <h>50.344608306884766</h>
      <w>14.753379821777344</w>
      <angle>0.5050726952122444</angle>
    </robndbox>
  </object>
  <object>
    <type>robndbox</type>
    <name>ship</name>
    <difficult>0</difficult>
    <robndbox>
      <cx>22.1593</cx>
      <cy>210.8787</cy>
      <h>40.673492431640625</h>
      <w>12.685711860656738</w>
      <angle>0.2350728185607389</angle>
    </robndbox>
  </object>
  <object>
    <type>robndbox</type>
    <name>ship</name>
    <difficult>0</difficult>
    <robndbox>
      <cx>193.616</cx>
      <cy>386.531</cy>
      <h>36.967613220214844</h>
      <w>13.135120391845703</w>
      <angle>0.5050731279759215</angle>
    </robndbox>
  </object>
</annotation>
